protobrain/__init__.py
protobrain/__version__.py
protobrain/brain.py
protobrain/computation.py
protobrain/learning.py
protobrain/neuron.py
protobrain/sensor.py
protobrain/synapses.py
protobrain/cli/__init__.py
protobrain/cli/experiment.py
protobrain/encoders/__init__.py
protobrain/encoders/numerical.py
protobrain/proto/__init__.py
protobrain/proto/encoder_pb2.py
protobrain/proto/experiment_pb2.py
protobrain/proto/sdr_pb2.py
protobrain/proto/snapshot_pb2.py
protobrain/util/__init__.py
protobrain/util/proto_io.py
protobrain/util/proto_parse.py
protobrain-0.0.3.dist-info/DESCRIPTION.rst
protobrain-0.0.3.dist-info/METADATA
protobrain-0.0.3.dist-info/RECORD
protobrain-0.0.3.dist-info/WHEEL
protobrain-0.0.3.dist-info/entry_points.txt
protobrain-0.0.3.dist-info/metadata.json
protobrain-0.0.3.dist-info/top_level.txt
