Metadata-Version: 2.0
Name: protobrain
Version: 0.0.3
Summary: Experimental project for machine learning.
Home-page: https://github.com/Ariel-Perez/protobrain
Author: Ariel Perez
Author-email: arielperezch@gmail.com
License: MIT
Platform: UNKNOWN
Classifier: License :: OSI Approved :: MIT License
Classifier: Programming Language :: Python
Classifier: Programming Language :: Python :: 3
Classifier: Programming Language :: Python :: 3.6
Classifier: Programming Language :: Python :: Implementation :: CPython
Classifier: Programming Language :: Python :: Implementation :: PyPy
Requires-Python: >=3.6.0
Requires-Dist: numpy
Requires-Dist: protobuf
